{
  "data": [
    {
      "title": "随机",
      "words": [
        "洗发水",
        "奥运会",
        "白龙马",
        "春晚",
        "饺子",
        "刷牙",
        "毛巾",
        "肥皂",
        "过年",
        "嚎啕大哭",
        "射击",
        "旱鸭子",
        "小鸟依人",
        "打嗝",
        "扭秧歌",
        "一毛不拔",
        "孙悟空",
        "暴跳如雷",
        "淘宝",
        "大跌眼镜",
        "八卦",
        "画饼充饥",
        "奶瓶",
        "羊入虎口",
        "闭月羞花",
        "足球",
        "泰山压顶",
        "打酱油",
        "老鹰",
        "皮鞋",
        "加油站",
        "香蕉",
        "猩猩",
        "井底之蛙",
        "吃货",
        "击剑",
        "一石二鸟",
        "啤酒肚",
        "含笑九泉",
        "我爱你",
        "睡觉",
        "吃里扒外",
        "机不可失",
        "打麻将",
        "呆若木鸡",
        "大眼瞪小眼",
        "百里挑一",
        "鼠标",
        "一刀两断",
        "井底之蛙",
        "嬉皮笑脸",
        "香水",
        "开膛破肚",
        "鸭子",
        "七上八下",
        "方便面",
        "外星人",
        "企鹅",
        "心花怒放",
        "见钱眼开",
        "西瓜",
        "流口水",
        "馒头",
        "牛头马面",
        "鸡飞蛋打",
        "豆腐",
        "狗急跳墙",
        "油条",
        "张牙舞爪",
        "回眸一笑",
        "美女",
        "照镜子",
        "秋裤",
        "猪八戒",
        "跪地求饶",
        "最炫民族风",
        "打呼噜",
        "跨栏",
        "石榴",
        "洗澡",
        "狼吞虎咽",
        "沉鱼落雁",
        "公鸡打鸣",
        "海枯石烂",
        "手套",
        "斗地主",
        "狼心狗肺",
        "老鼠",
        "拔河",
        "飞机",
        "弱不禁风",
        "女汉子",
        "痛哭流涕",
        "苹果",
        "鹤立鸡群",
        "贼眉鼠眼",
        "沙和尚",
        "雨女无瓜",
        "奥利给",
        "giao",
        "您配吗",
        "py交易",
        "MDZZ",
        "OJBK",
        "无fuck说",
        "AWSL",
        "十动然拒",
        "累觉不爱",
        "人艰不拆",
        "喜大普奔",
        "男默女泪",
        "细思极恐",
        "李菊福",
        "语死早",
        "来信砍",
        "一百块都不给我",
        "然并卵",
        "城会玩",
        "破事水",
        "无图言吊",
        "气突苏",
        "疯狂输出",
        "喜当爹",
        "蓝瘦香菇",
        "常威殴打来福",
        "我太难了",
        "给力",
        "走你",
        "浑身难受",
        "万万没想到",
        "大力哥",
        "杯具",
        "蛋定",
        "我好方",
        "泪流满面",
        "左右为难",
        "难上加难",
        "迎难而上",
        "药店碧莲",
        "河蟹",
        "果照",
        "吃枣药丸",
        "蛇精病",
        "石乐志",
        "扎心",
        "怼",
        "你造吗",
        "我宣你",
        "我到河北省来",
        "钞能力",
        "姿势",
        "舅服你",
        "冰阔落",
        "虾仁猪心",
        "2333",
        "C位",
        "胖次",
        "工口",
        "思密达",
        "西八",
        "帝都",
        "魔都",
        "阿卡林",
        "凯申物流",
        "圣母",
        "女权",
        "尼哥",
        "屌爆了",
        "毛妹",
        "天龙人",
        "索尼大法好",
        "索尼罪恶滔天",
        "我全都要",
        "还说你不会武功",
        "我信了你的鬼",
        "让我康康",
        "彬彬就是逊",
        "村口集合",
        "坟头蹦迪",
        "灵车漂移",
        "skr",
        "佛系",
        "官宣",
        "皮一下",
        "皮皮虾",
        "土味情话",
        "且行且珍惜",
        "很傻很天真",
        "很黄很暴力",
        "hxd",
        "gkd",
        "真香",
        "是个狼人",
        "厉害了我的哥",
        "杠精",
        "打call",
        "老司机",
        "小老弟",
        "大兄弟",
        "辣眼睛",
        "战斗民族",
        "洪荒之力",
        "怪我咯",
        "贾君鹏",
        "撩妹",
        "自带水泥",
        "杀马特",
        "忘了爱",
        "龙傲天",
        "玛丽苏",
        "梨",
        "桃",
        "橙子",
        "老虎",
        "狮子",
        "大象",
        "豹子",
        "猫",
        "狗",
        "狼",
        "蛇",
        "牛",
        "兔子",
        "龙",
        "马",
        "羊",
        "猴子",
        "公鸡",
        "母鸡",
        "猪"
      ]
    },
    {
      "title": "合家欢",
      "words": [
        "洗发水",
        "奥运会",
        "白龙马",
        "春晚",
        "饺子",
        "刷牙",
        "毛巾",
        "肥皂",
        "过年",
        "嚎啕大哭",
        "射击",
        "旱鸭子",
        "小鸟依人",
        "打嗝",
        "扭秧歌",
        "一毛不拔",
        "孙悟空",
        "暴跳如雷",
        "淘宝",
        "大跌眼镜",
        "八卦",
        "画饼充饥",
        "奶瓶",
        "羊入虎口",
        "闭月羞花",
        "足球",
        "泰山压顶",
        "打酱油",
        "老鹰",
        "皮鞋",
        "加油站",
        "香蕉",
        "猩猩",
        "井底之蛙",
        "吃货",
        "击剑",
        "一石二鸟",
        "啤酒肚",
        "含笑九泉",
        "我爱你",
        "睡觉",
        "吃里扒外",
        "机不可失",
        "打麻将",
        "呆若木鸡",
        "大眼瞪小眼",
        "百里挑一",
        "鼠标",
        "一刀两断",
        "井底之蛙",
        "嬉皮笑脸",
        "香水",
        "开膛破肚",
        "鸭子",
        "七上八下",
        "方便面",
        "外星人",
        "企鹅",
        "心花怒放",
        "见钱眼开",
        "西瓜",
        "流口水",
        "馒头",
        "牛头马面",
        "鸡飞蛋打",
        "豆腐",
        "狗急跳墙",
        "油条",
        "张牙舞爪",
        "回眸一笑",
        "美女",
        "照镜子",
        "秋裤",
        "猪八戒",
        "跪地求饶",
        "最炫民族风",
        "打呼噜",
        "跨栏",
        "石榴",
        "洗澡",
        "狼吞虎咽",
        "沉鱼落雁",
        "公鸡打鸣",
        "海枯石烂",
        "手套",
        "斗地主",
        "狼心狗肺",
        "老鼠",
        "拔河",
        "飞机",
        "弱不禁风",
        "女汉子",
        "痛哭流涕",
        "苹果",
        "鹤立鸡群",
        "贼眉鼠眼",
        "沙和尚",
        "梨",
        "桃",
        "橙子",
        "老虎",
        "狮子",
        "大象",
        "豹子",
        "猫",
        "狗",
        "狼",
        "蛇",
        "牛",
        "兔子",
        "龙",
        "马",
        "羊",
        "猴子",
        "公鸡",
        "母鸡",
        "猪"
      ]
    },
    {
      "title": "网络用语",
      "words": [
        "雨女无瓜",
        "奥利给",
        "giao",
        "您配吗",
        "py交易",
        "MDZZ",
        "OJBK",
        "无fuck说",
        "AWSL",
        "十动然拒",
        "累觉不爱",
        "人艰不拆",
        "喜大普奔",
        "男默女泪",
        "细思极恐",
        "李菊福",
        "语死早",
        "来信砍",
        "一百块都不给我",
        "然并卵",
        "城会玩",
        "破事水",
        "无图言吊",
        "气突苏",
        "疯狂输出",
        "喜当爹",
        "蓝瘦香菇",
        "常威殴打来福",
        "我太难了",
        "给力",
        "走你",
        "浑身难受",
        "万万没想到",
        "大力哥",
        "杯具",
        "蛋定",
        "我好方",
        "泪流满面",
        "左右为难",
        "难上加难",
        "迎难而上",
        "药店碧莲",
        "河蟹",
        "果照",
        "吃枣药丸",
        "蛇精病",
        "石乐志",
        "扎心",
        "怼",
        "你造吗",
        "我宣你",
        "我到河北省来",
        "钞能力",
        "姿势",
        "舅服你",
        "冰阔落",
        "虾仁猪心",
        "2333",
        "C位",
        "胖次",
        "工口",
        "思密达",
        "西八",
        "帝都",
        "魔都",
        "阿卡林",
        "凯申物流",
        "圣母",
        "女权",
        "尼哥",
        "屌爆了",
        "毛妹",
        "天龙人",
        "索尼大法好",
        "索尼罪恶滔天",
        "我全都要",
        "还说你不会武功",
        "我信了你的鬼",
        "让我康康",
        "彬彬就是逊",
        "村口集合",
        "坟头蹦迪",
        "灵车漂移",
        "skr",
        "佛系",
        "官宣",
        "皮一下",
        "皮皮虾",
        "土味情话",
        "且行且珍惜",
        "很傻很天真",
        "很黄很暴力",
        "hxd",
        "gkd",
        "真香",
        "是个狼人",
        "厉害了我的哥",
        "杠精",
        "打call",
        "老司机",
        "小老弟",
        "大兄弟",
        "辣眼睛",
        "战斗民族",
        "洪荒之力",
        "怪我咯",
        "贾君鹏",
        "撩妹",
        "自带水泥",
        "杀马特",
        "忘了爱",
        "龙傲天",
        "玛丽苏"
      ]
    }
  ]
}